django_funcache-0.1.0.dist-info/licenses/LICENCE.txt
django_funcache-0.1.0.dist-info/licenses/LICENSE
funcache/__init__.py
funcache/apps.py
funcache/signals.py
funcache/utils.py
funcache/migrations/__init__.py
django_funcache-0.1.0.dist-info/METADATA
django_funcache-0.1.0.dist-info/WHEEL
django_funcache-0.1.0.dist-info/top_level.txt
django_funcache-0.1.0.dist-info/RECORD
