Metadata-Version: 2.4
Name: django-funcache
Version: 0.1.0
Summary: Add your description here
Requires-Python: >=3.13
License-File: LICENCE.txt
License-File: LICENSE
Requires-Dist: build>=1.2.2.post1
Requires-Dist: django>=5.1.8
Requires-Dist: twine>=6.1.0
Dynamic: license-file
